orekit_jcc/__init__.py
orekit_jcc/_orekit_jcc.cpython-313-x86_64-linux-gnu.so
orekit_jcc/binder.so
orekit_jcc/windows.py
orekit_jcc/graalvm/libjvm.so
orekit_jcc/resources/GEOID/egm96.grd
orekit_jcc/resources/GEOID/egm96.grd.aux.xml
orekit_jcc/resources/GEOID/egm96.grd.hdr
orekit_jcc/resources/GEOID/egm96_15.gtx
orekit_jcc/resources/GEOID/egm96_15.gtx.aux.xml
orekit_jcc/resources/GEOID/readme.txt
orekit_jcc/resources/orekit-data/UTC-TAI.history
orekit_jcc/resources/orekit-data/DE-430-ephemerides/lnxp1990.430
orekit_jcc/resources/orekit-data/Potential/eigen-6s.gfc
orekit_jcc-13.2.1.dist-info/METADATA
orekit_jcc-13.2.1.dist-info/WHEEL
orekit_jcc-13.2.1.dist-info/top_level.txt
orekit_jcc-13.2.1.dist-info/RECORD
orekit_jcc-13.2.1.dist-info/licenses/LICENSE
orekit_jcc-13.2.1.dist-info/licenses/NOTICE
