Metadata-Version: 2.4
Name: orekit_jcc
Version: 13.2.1
License-File: LICENSE
License-File: NOTICE
Dynamic: license-file
